setup.py
awsbots/__init__.py
awsbots.egg-info/PKG-INFO
awsbots.egg-info/SOURCES.txt
awsbots.egg-info/dependency_links.txt
awsbots.egg-info/not-zip-safe
awsbots.egg-info/requires.txt
awsbots.egg-info/top_level.txt
awsbots/examples/__init__.py
awsbots/examples/echo_bot.py
awsbots/lib/__init__.py
awsbots/lib/bots/__init__.py
awsbots/lib/bots/bot.py
awsbots/lib/bots/messenger_bot.py
awsbots/lib/util/__init__.py
awsbots/lib/util/handler.py
awsbots/lib/util/registry.py