Metadata-Version: 1.0
Name: awsbots
Version: 0.1
Summary: Conversational bot platform based on AWS
Home-page: http://github.com/tfranovic/awsbots
Author: Tin Franovic
Author-email: tin.franovic@gmail.com
License: MIT
Platform: UNKNOWN
